py_calculator/__init__.py
py_calculator/calculator.py
py_calculator_test-0.1.2.dist-info/licenses/LICENSE
py_calculator_test-0.1.2.dist-info/METADATA
py_calculator_test-0.1.2.dist-info/WHEEL
py_calculator_test-0.1.2.dist-info/top_level.txt
py_calculator_test-0.1.2.dist-info/RECORD
