Metadata-Version: 2.4
Name: py-calculator-test
Version: 0.1.2
Summary: Simple Python calculator package
Author: Mounika Beerelly
License: MIT
Classifier: Programming Language :: Python :: 3
Classifier: License :: OSI Approved :: MIT License
Classifier: Operating System :: OS Independent
Requires-Python: >=3.8
License-File: LICENSE
Dynamic: license-file
